shared_hashmap/__init__.py
shared_hashmap/shared_hashmap.py
shared_hashmap-0.2.0.dist-info/METADATA
shared_hashmap-0.2.0.dist-info/WHEEL
shared_hashmap-0.2.0.dist-info/top_level.txt
shared_hashmap-0.2.0.dist-info/RECORD
