Metadata-Version: 2.4
Name: shared_hashmap
Version: 0.2.0
Summary: High-performance cross-process shared memory hashmap for Python multiprocessing
Author-email: Raymond Chastain <RaymondLC92@protonmail.com>
License: MIT
Keywords: multiprocessing,shared-memory,hashmap,concurrent,atomic
Classifier: Development Status :: 4 - Beta
Classifier: Intended Audience :: Developers
Classifier: License :: OSI Approved :: MIT License
Classifier: Programming Language :: Python :: 3
Classifier: Programming Language :: Python :: 3.8
Classifier: Programming Language :: Python :: 3.9
Classifier: Programming Language :: Python :: 3.10
Classifier: Programming Language :: Python :: 3.11
Classifier: Programming Language :: Python :: 3.12
Classifier: Programming Language :: Python :: 3.13
Classifier: Topic :: Software Development :: Libraries :: Python Modules
Classifier: Topic :: System :: Distributed Computing
Requires-Python: >=3.9
Requires-Dist: atomics>=1.0.3
